clock_generation/clock_tb.sv
`timescale 1ns / 1ps

module tb;

  reg clk = 0;
  reg clk50 = 0;

  // Generate 100 MHz clock (10 ns period)
  always #5 clk = ~clk;

  // Clock generation parameters
  real phase;
  real ton;
  real toff;

  // Task to calculate ton and toff based on frequency and duty cycle
  task calc (
    input real freq_hz,
    input real duty_cycle,
    input real phase_ns,
    output real phase_out,
    output real ton_out,
    output real toff_out
  );
    begin
      phase_out = phase_ns;
      ton_out = (1.0 / freq_hz) * duty_cycle * 1e9;  // ns
      toff_out = (1e9 / freq_hz) - ton_out;          // ns
    end
  endtask

  // Task to generate clock with given ton, toff, and phase
  task clkgen (
    input real phase_ns,
    input real ton_ns,
    input real toff_ns
  );
    integer i;
    begin
      @(posedge clk);
      #phase_ns;
      for (i = 0; i < 10; i = i + 1) begin // generate 10 pulses
        clk50 = 1;
        #ton_ns;
        clk50 = 0;
        #toff_ns;
      end
    end
  endtask

  // Initialize and run
  initial begin
    calc(100_000_000, 0.1, 2, phase, ton, toff); // 100 MHz, 10% duty, 2 ns phase
    clkgen(phase, ton, toff);
    $finish;
  end

  initial begin
    $dumpfile("dut.vcd");
    $dumpvars(0, tb);
  end

endmodule

clock_generation/dut.vcd
$date
Wed Jul  9 13:57:59 2025
$end
$version
Riviera-PRO Version 2023.04.112.8911
$end
$timescale
1 ps
$end

$scope module tb $end
$var reg 1 ! clk $end
$var reg 1 " clk50 $end
$var real 64 # phase $end
$var real 64 $ ton $end
$var real 64 % toff $end

$scope task calc $end
$var real 64 & freq_hz $end
$var real 64 ' duty_cycle $end
$var real 64 ( phase_ns $end
$var real 64 ) phase_out $end
$var real 64 * ton_out $end
$var real 64 + toff_out $end
$upscope $end


$scope task clkgen $end
$var real 64 , phase_ns $end
$var real 64 - ton_ns $end
$var real 64 . toff_ns $end
$var integer 32 / i $end
$upscope $end

$upscope $end

$enddefinitions $end
$dumpvars
0!
0"
r2 #
r1 $
r9 %
r100000000 &
r0.1 '
r2 (
r2 )
r1 *
r9 +
r2 ,
r1 -
r9 .
bx /
$end
#5000
1!
#7000
b0 /
1"
#8000
0"
#10000
0!
#15000
1!
#17000
b1 /
1"
#18000
0"
#20000
0!
#25000
1!
#27000
b10 /
1"
#28000
0"
#30000
0!
#35000
1!
#37000
b11 /
1"
#38000
0"
#40000
0!
#45000
1!
#47000
b100 /
1"
#48000
0"
#50000
0!
#55000
1!
#57000
b101 /
1"
#58000
0"
#60000
0!
#65000
1!
#67000
b110 /
1"
#68000
0"
#70000
0!
#75000
1!
#77000
b111 /
1"
#78000
0"
#80000
0!
#85000
1!
#87000
b1000 /
1"
#88000
0"
#90000
0!
#95000
1!
#97000
b1001 /
1"
#98000
0"
#100000
0!
#105000
1!
#107000
b1010 /
